guillotina_localstorage/__init__.py
guillotina_localstorage/adapters.py
guillotina_localstorage/interfaces.py
guillotina_localstorage/storage.py
guillotina_localstorage/tests/__init__.py
guillotina_localstorage/tests/conftest.py
guillotina_localstorage/tests/fixtures.py
guillotina_localstorage/tests/test_storage.py
guillotina_localstorage/utils.py
guillotina_localstorage-0.2.0.dist-info/LICENSE
guillotina_localstorage-0.2.0.dist-info/WHEEL
guillotina_localstorage-0.2.0.dist-info/METADATA
guillotina_localstorage-0.2.0.dist-info/RECORD
