Metadata-Version: 2.1
Name: guillotina-localstorage
Version: 0.2.0
Summary: Local FS storage support for Guillotina
License: GPL-3.0-only
Author: Jordi Masip
Author-email: jordi@masip.cat
Requires-Python: >=3.7,<4.0
Classifier: License :: OSI Approved :: GNU General Public License v3 (GPLv3)
Classifier: Programming Language :: Python :: 3
Classifier: Programming Language :: Python :: 3.7
Classifier: Programming Language :: Python :: 3.8
Classifier: Programming Language :: Python :: 3.9
Requires-Dist: aiofiles (>=0.7.0,<0.8.0)
Requires-Dist: guillotina (>5.3.48)
